markdown_table_generator/__init__.py
markdown_table_generator/markdown_table_generator.py
markdown_table_generator-1.1.0.dist-info/LICENSE
markdown_table_generator-1.1.0.dist-info/METADATA
markdown_table_generator-1.1.0.dist-info/WHEEL
markdown_table_generator-1.1.0.dist-info/entry_points.txt
markdown_table_generator-1.1.0.dist-info/top_level.txt
markdown_table_generator-1.1.0.dist-info/RECORD
