Metadata-Version: 2.1
Name: markdown-table-generator
Version: 1.1.0
Summary: Library to generate Markdown table
Home-page: https://github.com/leroyguillaume/py-markdown-table-generator
Author: Guillaume Leroy
Author-email: pro.guillaume.leroy@gmail.com
License: UNKNOWN
Platform: UNKNOWN
Classifier: Programming Language :: Python :: 3
Classifier: License :: OSI Approved :: MIT License
Classifier: Operating System :: OS Independent
Requires-Python: >=3.6
License-File: LICENSE
Requires-Dist: typing
